setup.py
AASMessenger_Client.egg-info/PKG-INFO
AASMessenger_Client.egg-info/SOURCES.txt
AASMessenger_Client.egg-info/dependency_links.txt
AASMessenger_Client.egg-info/requires.txt
AASMessenger_Client.egg-info/top_level.txt
client/__init__.py
client/client.py
client/setup_client.py
client/client/__init__.py
client/client/add_contact.py
client/client/database.py
client/client/del_contact.py
client/client/main_window.py
client/client/main_window_conv.py
client/client/start_dialog.py
client/client/transport.py
client/common/__init__.py
client/common/decos.py
client/common/descriptors.py
client/common/errors.py
client/common/metaclasses.py
client/common/settings.py
client/common/utils.py
client/doc/__init__.py
client/doc/source/__init__.py
client/doc/source/conf.py
client/log/__init__.py
client/log/client_log_config.py
client/log/server_log_config.py
client/unit_tests/__init__.py