Metadata-Version: 1.0
Name: AASMessenger-Client
Version: 1.0.1
Summary: Messenger_Client
Home-page: UNKNOWN
Author: Anton Sobolev
Author-email: antony.sobolev@gmail.com
License: UNKNOWN
Platform: UNKNOWN
